pypyr/__init__.py
pypyr/__main__.py
pypyr/cli.py
pypyr/config.py
pypyr/context.py
pypyr/dsl.py
pypyr/errors.py
pypyr/formatting.py
pypyr/moduleloader.py
pypyr/pipedef.py
pypyr/pipeline.py
pypyr/pipelinerunner.py
pypyr/platform.py
pypyr/py.typed
pypyr/retries.py
pypyr/stepsrunner.py
pypyr/subproc.py
pypyr/toml.py
pypyr/venv.py
pypyr/version.py
pypyr/yaml.py
pypyr/aio/__init__.py
pypyr/aio/subproc.py
pypyr/cache/__init__.py
pypyr/cache/admin.py
pypyr/cache/backoffcache.py
pypyr/cache/cache.py
pypyr/cache/filecache.py
pypyr/cache/loadercache.py
pypyr/cache/namespacecache.py
pypyr/cache/parsercache.py
pypyr/cache/stepcache.py
pypyr/loaders/__init__.py
pypyr/loaders/file.py
pypyr/loaders/string.py
pypyr/log/__init__.py
pypyr/log/logger.py
pypyr/parser/__init__.py
pypyr/parser/argskwargs.py
pypyr/parser/dict.py
pypyr/parser/json.py
pypyr/parser/jsonfile.py
pypyr/parser/keys.py
pypyr/parser/keyvaluepairs.py
pypyr/parser/list.py
pypyr/parser/string.py
pypyr/parser/tomlfile.py
pypyr/parser/yamlfile.py
pypyr/pipelines/config-show.yaml
pypyr/pipelines/donothing.yaml
pypyr/pipelines/echo.yaml
pypyr/pipelines/magritte.yaml
pypyr/pipelines/pypyrversion.yaml
pypyr/pipelines/venv-create.yaml
pypyr/steps/__init__.py
pypyr/steps/add.py
pypyr/steps/append.py
pypyr/steps/assert.py
pypyr/steps/call.py
pypyr/steps/cmd.py
pypyr/steps/cmds.py
pypyr/steps/configvars.py
pypyr/steps/contextclear.py
pypyr/steps/contextclearall.py
pypyr/steps/contextcopy.py
pypyr/steps/contextmerge.py
pypyr/steps/contextsetf.py
pypyr/steps/debug.py
pypyr/steps/default.py
pypyr/steps/echo.py
pypyr/steps/env.py
pypyr/steps/envget.py
pypyr/steps/fetchjson.py
pypyr/steps/fetchtoml.py
pypyr/steps/fetchyaml.py
pypyr/steps/fileformat.py
pypyr/steps/fileformatjson.py
pypyr/steps/fileformattoml.py
pypyr/steps/fileformatyaml.py
pypyr/steps/fileread.py
pypyr/steps/filereplace.py
pypyr/steps/filewrite.py
pypyr/steps/filewritejson.py
pypyr/steps/filewritetoml.py
pypyr/steps/filewriteyaml.py
pypyr/steps/glob.py
pypyr-5.9.1.dist-info/entry_points.txt
pypyr-5.9.1.dist-info/LICENSE
pypyr-5.9.1.dist-info/WHEEL
pypyr-5.9.1.dist-info/METADATA
pypyr-5.9.1.dist-info/RECORD
