Metadata-Version: 2.1
Name: pypyr
Version: 5.9.1
Summary: task-runner for automation pipelines defined in yaml. cli & api.
Keywords: task-runner,automation,devops,ci/cd,pipeline runner
Author-email: Thomas Gaigher <info@pypyr.io>
Requires-Python: >=3.7
Classifier: Development Status :: 5 - Production/Stable
Classifier: Intended Audience :: Developers
Classifier: Topic :: Software Development :: Build Tools
Classifier: Topic :: Software Development :: Libraries :: Python Modules
Classifier: Topic :: Utilities
Classifier: License :: OSI Approved :: Apache Software License
Classifier: Programming Language :: Python :: 3.7
Classifier: Programming Language :: Python :: 3.8
Classifier: Programming Language :: Python :: 3.9
Classifier: Programming Language :: Python :: 3.10
Classifier: Programming Language :: Python :: 3.11
Classifier: Typing :: Typed
Requires-Dist: python-dateutil
Requires-Dist: ruamel.yaml >= 0.17.32
Requires-Dist: tomli >= 1.1.0 ; python_version < '3.11'
Requires-Dist: tomli-w
Requires-Dist: bumpversion ; extra == "dev"
Requires-Dist: coverage ; extra == "dev"
Requires-Dist: flake8 ; extra == "dev"
Requires-Dist: flake8-docstrings ; extra == "dev"
Requires-Dist: flit ; extra == "dev"
Requires-Dist: pyfakefs ; extra == "dev"
Requires-Dist: pytest ; extra == "dev"
Project-URL: Documentation, https://pypyr.io/docs/
Project-URL: Home, https://pypyr.io
Project-URL: Release Notes, https://pypyr.io/updates/releases/
Project-URL: Source, https://github.com/pypyr/pypyr/
Project-URL: Tracker, https://github.com/pypyr/pypyr/issues
Project-URL: Twitter, https://twitter.com/pypyrpipes
Provides-Extra: dev
